{"errors":[],"warnings":[],"namedChunkGroups":{"app":{"chunks":[5,0,2],"assets":["webpack-runtime-b002c76134753121b482.js","webpack-runtime-b002c76134753121b482.js.map","commons-36ba911827844ec2cde5.js","commons-36ba911827844ec2cde5.js.map","app-a966496075a1d51111ff.js","app-a966496075a1d51111ff.js.map"],"children":{},"childAssets":{}},"component---src-pages-index-js":{"chunks":[1,0,3],"assets":["styles.144144672c65c0fcd209.css","styles-04367093563754e2a6bc.js","styles-04367093563754e2a6bc.js.map","commons-36ba911827844ec2cde5.js","commons-36ba911827844ec2cde5.js.map","component---src-pages-index-js-e9d05cf8bed16643202b.js","component---src-pages-index-js-e9d05cf8bed16643202b.js.map"],"children":{},"childAssets":{}},"component---src-pages-sweden-js":{"chunks":[1,0,4],"assets":["styles.144144672c65c0fcd209.css","styles-04367093563754e2a6bc.js","styles-04367093563754e2a6bc.js.map","commons-36ba911827844ec2cde5.js","commons-36ba911827844ec2cde5.js.map","component---src-pages-sweden-js-9b0c8187bcb2e3649a31.js","component---src-pages-sweden-js-9b0c8187bcb2e3649a31.js.map"],"children":{},"childAssets":{}}},"assetsByChunkName":{"app":["webpack-runtime-b002c76134753121b482.js","commons-36ba911827844ec2cde5.js","app-a966496075a1d51111ff.js"],"component---src-pages-index-js":["styles.144144672c65c0fcd209.css","styles-04367093563754e2a6bc.js","commons-36ba911827844ec2cde5.js","component---src-pages-index-js-e9d05cf8bed16643202b.js"],"component---src-pages-sweden-js":["styles.144144672c65c0fcd209.css","styles-04367093563754e2a6bc.js","commons-36ba911827844ec2cde5.js","component---src-pages-sweden-js-9b0c8187bcb2e3649a31.js"]}}